// class version 54.0 (54)
// access flags 0x21
public class bank/Customer {

  // compiled from: Customer.java
  // access flags 0x19
  public final static INNERCLASS java/lang/invoke/MethodHandles$Lookup java/lang/invoke/MethodHandles Lookup

  // access flags 0x2
  private Ljava/lang/String; name

  // access flags 0x2
  private Ljava/lang/String; accountNumber

  // access flags 0x2
  private I balance

  // access flags 0x1
  public <init>(Ljava/lang/String;Ljava/lang/String;I)V
   L0
    LINENUMBER 29 L0
    ALOAD 0
    INVOKESPECIAL java/lang/Object.<init> ()V
   L1
    LINENUMBER 32 L1
    ILOAD 3
    IFGE L2
   L3
    LINENUMBER 33 L3
    NEW java/lang/IllegalArgumentException
    DUP
    LDC "Balance must be >= 0"
    INVOKESPECIAL java/lang/IllegalArgumentException.<init> (Ljava/lang/String;)V
    ATHROW
   L2
    LINENUMBER 37 L2
   FRAME FULL [bank/Customer java/lang/String java/lang/String I] []
    ALOAD 2
    INVOKEVIRTUAL java/lang/String.length ()I
    BIPUSH 14
    IF_ICMPEQ L4
   L5
    LINENUMBER 38 L5
    NEW java/lang/IllegalArgumentException
    DUP
    LDC "Account number must be 14 characters long"
    INVOKESPECIAL java/lang/IllegalArgumentException.<init> (Ljava/lang/String;)V
    ATHROW
   L4
    LINENUMBER 39 L4
   FRAME FULL [bank/Customer java/lang/String java/lang/String I] []
    ALOAD 2
    ICONST_0
    ICONST_3
    INVOKEVIRTUAL java/lang/String.substring (II)Ljava/lang/String;
    LDC "091"
    INVOKEVIRTUAL java/lang/String.equals (Ljava/lang/Object;)Z
    IFNE L6
   L7
    LINENUMBER 40 L7
    NEW java/lang/IllegalArgumentException
    DUP
    LDC "The first three characters must be '091'"
    INVOKESPECIAL java/lang/IllegalArgumentException.<init> (Ljava/lang/String;)V
    ATHROW
   L6
    LINENUMBER 41 L6
   FRAME FULL [bank/Customer java/lang/String java/lang/String I] []
    ALOAD 2
    ICONST_3
    INVOKEVIRTUAL java/lang/String.charAt (I)C
    BIPUSH 45
    IF_ICMPNE L8
    ALOAD 2
    BIPUSH 11
    INVOKEVIRTUAL java/lang/String.charAt (I)C
    BIPUSH 45
    IF_ICMPEQ L9
   L8
    LINENUMBER 42 L8
   FRAME FULL [bank/Customer java/lang/String java/lang/String I] []
    NEW java/lang/IllegalArgumentException
    DUP
    LDC "Account number is not correctly separated by '-'"
    INVOKESPECIAL java/lang/IllegalArgumentException.<init> (Ljava/lang/String;)V
    ATHROW
   L9
    LINENUMBER 43 L9
   FRAME FULL [bank/Customer java/lang/String java/lang/String I] []
    ALOAD 2
    ICONST_0
    ICONST_3
    INVOKEVIRTUAL java/lang/String.substring (II)Ljava/lang/String;
    ALOAD 2
    ICONST_4
    BIPUSH 7
    INVOKEVIRTUAL java/lang/String.substring (II)Ljava/lang/String;
    INVOKEDYNAMIC makeConcatWithConstants(Ljava/lang/String;Ljava/lang/String;)Ljava/lang/String; [
      // handle kind 0x6 : INVOKESTATIC
      java/lang/invoke/StringConcatFactory.makeConcatWithConstants(Ljava/lang/invoke/MethodHandles$Lookup;Ljava/lang/String;Ljava/lang/invoke/MethodType;Ljava/lang/String;[Ljava/lang/Object;)Ljava/lang/invoke/CallSite;
      // arguments:
      "\u0001\u0001"
    ]
    INVOKESTATIC java/lang/Integer.parseInt (Ljava/lang/String;)I
    BIPUSH 97
    IREM
    ALOAD 2
    BIPUSH 12
    BIPUSH 14
    INVOKEVIRTUAL java/lang/String.substring (II)Ljava/lang/String;
    INVOKESTATIC java/lang/Integer.parseInt (Ljava/lang/String;)I
    IF_ICMPEQ L10
   L11
    LINENUMBER 44 L11
    NEW java/lang/IllegalArgumentException
    DUP
    LDC "Control numbers are wrong"
    INVOKESPECIAL java/lang/IllegalArgumentException.<init> (Ljava/lang/String;)V
    ATHROW
   L10
    LINENUMBER 47 L10
   FRAME FULL [bank/Customer java/lang/String java/lang/String I] []
    ALOAD 0
    ALOAD 1
    PUTFIELD bank/Customer.name : Ljava/lang/String;
   L12
    LINENUMBER 48 L12
    ALOAD 0
    ALOAD 2
    PUTFIELD bank/Customer.accountNumber : Ljava/lang/String;
   L13
    LINENUMBER 49 L13
    ALOAD 0
    ILOAD 3
    PUTFIELD bank/Customer.balance : I
   L14
    LINENUMBER 50 L14
    RETURN
   L15
    LOCALVARIABLE this Lbank/Customer; L0 L15 0
    LOCALVARIABLE name Ljava/lang/String; L0 L15 1
    LOCALVARIABLE accountNumber Ljava/lang/String; L0 L15 2
    LOCALVARIABLE balance I L0 L15 3
    MAXSTACK = 4
    MAXLOCALS = 4

  // access flags 0x1
  public getName()Ljava/lang/String;
   L0
    LINENUMBER 58 L0
    ALOAD 0
    GETFIELD bank/Customer.name : Ljava/lang/String;
    ARETURN
   L1
    LOCALVARIABLE this Lbank/Customer; L0 L1 0
    MAXSTACK = 1
    MAXLOCALS = 1

  // access flags 0x1
  public getAccountNumber()Ljava/lang/String;
   L0
    LINENUMBER 67 L0
    ALOAD 0
    GETFIELD bank/Customer.accountNumber : Ljava/lang/String;
    ARETURN
   L1
    LOCALVARIABLE this Lbank/Customer; L0 L1 0
    MAXSTACK = 1
    MAXLOCALS = 1

  // access flags 0x1
  public getBalance()I
   L0
    LINENUMBER 76 L0
    ALOAD 0
    GETFIELD bank/Customer.balance : I
    IFEQ L1
    ICONST_0
    IRETURN
   L1
   FRAME FULL [bank/Customer] []
    ICONST_1
    IRETURN
   L2
    LOCALVARIABLE this Lbank/Customer; L0 L2 0
    MAXSTACK = 1
    MAXLOCALS = 1

  // access flags 0x1
  public setBalance(I)V
   L0
    LINENUMBER 85 L0
    ILOAD 1
    IFGE L1
   L2
    LINENUMBER 86 L2
    NEW java/lang/IllegalArgumentException
    DUP
    LDC "Balance must be >= 0"
    INVOKESPECIAL java/lang/IllegalArgumentException.<init> (Ljava/lang/String;)V
    ATHROW
   L1
    LINENUMBER 88 L1
   FRAME FULL [bank/Customer I] []
    ALOAD 0
    ILOAD 1
    PUTFIELD bank/Customer.balance : I
   L3
    LINENUMBER 89 L3
    RETURN
   L4
    LOCALVARIABLE this Lbank/Customer; L0 L4 0
    LOCALVARIABLE balance I L0 L4 1
    MAXSTACK = 3
    MAXLOCALS = 2
}

